{
  "authors": [
    "chickentuna"
  ],
  "description": "Fakutori is a laid-back and colorful automation game;\nplace machines, discover new elements, and try to craft the elusive Legendary Blocks!\nNo limits, no pressure, just blocks!",
  "game": "Fakutori",
  "github": "https://github.com/chickentuna/Archipelago-WeddingWitch",
  "license": null,
  "manifest_fields": [
    "authors",
    "minimum_ap_version",
    "world_version"
  ],
  "versions": {
    "v0.1.0": {
      "created_at": "2026-03-13T16:05:24Z",
      "description": "",
      "download_url": "https://github.com/chickentuna/Archipelago-WeddingWitch/releases/download/v0.1.0/fakutori.apworld",
      "has_manifest": true,
      "hash_sha256": "f0813ad0d50105bf8fd73efc18a0240e9e5d755dbc95a5831e352e1dbab4bc8f",
      "html_url": "https://github.com/chickentuna/Archipelago-WeddingWitch/releases/tag/v0.1.0",
      "minimum_ap_version": "0.6.2",
      "size": 9989,
      "source_url": "https://api.github.com/repos/chickentuna/Archipelago-WeddingWitch",
      "tag": "v0.1.0",
      "title": "fakutori apworld v0.1.0",
      "version_simple": "1.0.0",
      "world_version": "1.0.0"
    },
    "v0.1.1": {
      "created_at": "2026-03-25T07:53:42Z",
      "description": "- Fixed EvolvingFire recipe logic\r\n- Consistent minimum ap client version\r\n\r\nsee https://github.com/chickentuna/FakutoriRandomizer/releases for plugin",
      "download_url": "https://github.com/chickentuna/Archipelago-Fakutori/releases/download/v0.1.1/fakutori.apworld",
      "has_manifest": true,
      "hash_sha256": "54ff9fc2482a74a273370439b5fc3bac619e29cadccb1daba8952b29f59e1188",
      "html_url": "https://github.com/chickentuna/Archipelago-Fakutori/releases/tag/v0.1.1",
      "minimum_ap_version": "0.6.4",
      "size": 10009,
      "source_url": "https://api.github.com/repos/chickentuna/Archipelago-Fakutori",
      "tag": "v0.1.1",
      "title": "fakutori apworld v0.1.1",
      "version_simple": "0.1.1",
      "world_version": "0.1.1"
    },
    "v0.1.1r2": {
      "created_at": "2026-06-08T10:05:44Z",
      "description": "- **Asset rebuilt 2026-06-08:** fixed generation crashes \u2014 `KeyError: 'Quasar'` in set_rules for non-Quasar goals, `Extra shop` duplication with 2+ Fakutori players, and a multiworld `FillError` (filler under-count from the shared item pool); added manifest `compatible_version` so the world reports its version (0.1.1) correctly.\r\n- Fixed EvolvingFire recipe logic\r\n- Consistent minimum ap client version\r\n\r\nsee https://github.com/chickentuna/FakutoriRandomizer/releases for plugin",
      "download_url": "https://github.com/chickentuna/Archipelago-WeddingWitch/releases/download/v0.1.1/fakutori.apworld",
      "has_manifest": true,
      "hash_sha256": "0b846b128474c5c08a104ce0eafeeb14c98816c1cb2962cde320579ed24709d4",
      "html_url": "https://github.com/chickentuna/Archipelago-WeddingWitch/releases/tag/v0.1.1",
      "minimum_ap_version": "0.6.4",
      "size": 10502,
      "source_url": "https://api.github.com/repos/chickentuna/Archipelago-WeddingWitch",
      "tag": "v0.1.1r2",
      "title": "fakutori apworld v0.1.1",
      "version_simple": "0.1.1",
      "world_version": "0.1.1.post2"
    }
  }
}
