{
  "authors": [
    "1257Plays",
    "ericg"
  ],
  "description": "Jump and fly your way through danger in this rhythm-based action platformer!",
  "flags": [
    "unready"
  ],
  "game": "Geometry Dash",
  "github": "https://github.com/matorblal-byte/ArchipelagoGD2",
  "license": null,
  "manifest_fields": [],
  "versions": {
    "v1.0.0-alpha.1": {
      "created_at": "2026-03-15T01:19:20Z",
      "description": "Changelogs in changelogs.md \r\nAPWorld source code - https://github.com/matorblal-byte/APWorldForGDArch/tree/main/worlds\r\nAPCpp-gd source code - https://github.com/matorblal-byte/APCpp-gd\r\nSource code in in this repo if that wasnt clear already\r\nPlease report bugs thank you! \r\nPlanning to add modifers for the levels for replayability (i.e 1.25x speed)\r\nPlanning to add the whole reboot thing and new save file thing and stuffs\r\nPlanning to add portal checks and stuff (it works, but i havent put it in due to there being more items then locations and almost every level would be impossible with it (will probably have a solution by when i fix the more itemds than locations thing)\r\nPlanning to add room info after connected and disconnect button\r\nPreparing to add progressive gauntlets and or map packs \r\n## Things to consider\r\nCurrent release include debug buttons ignore them click the silver one\r\nCould softlock - If you beat all the levels that give 100 mana orbs, you will not be able to progress (because 100 mana orbs ends the path) (99% of this would happen solo)\r\nIf there is a save file loaded, notifications will get spammed\r\n~~Tower levels except the tower don't give items on completion for some reason~~ they do now!\r\nNo win state (so you might wanna release manually when you want)\r\nDeathlink is untested\r\nMultiworld is partially untested (i only tested with 1 yaml)(literally the most important thing but im confident)\r\nMacOS and Linux untested (what i mean by this is with wine and other stuffs that left you run windows applications)\r\n## How to import\r\nGet geode (i assume you have it)\r\nDownload both files, run the apworld to install it \r\nDrag the .geode into the mods folder (Right click in GD and press open local files, geode, mods, then drag it) \r\nOn the arch client, generate template options, options creator, generate, then host it (can't host on archipelago.gg) \r\nConnect to Archipelago with the top right button when you go into GD! \r\nShould now be in (if you havent port forwarded, use a loopback address (127.0.01) and use your port number, which you have to disable private firewall?)",
      "download_url": "https://github.com/matorblal-byte/ArchipelagoGD2/releases/download/v1.0.0-alpha.1/geometrydash.apworld",
      "has_manifest": false,
      "hash_sha256": "7c4f502fe2a1b47ae2465bd3cfc0b9293fe88bcd8f0f6deea6b791f5cab4e16a",
      "html_url": "https://github.com/matorblal-byte/ArchipelagoGD2/releases/tag/v1.0.0-alpha.1",
      "size": 5142,
      "source_url": "https://api.github.com/repos/matorblal-byte/ArchipelagoGD2",
      "tag": "v1.0.0-alpha.1",
      "title": "v1.0.0-alpha.1",
      "version_simple": "1.0.0",
      "world_version": "1.0.0a1"
    },
    "v1.0.0-alpha.10": {
      "created_at": "2026-04-13T00:08:00Z",
      "description": "Bugfix 7 (vector) update!\r\nChangelogs in [changelogs.md](https://github.com/matorblal-byte/ArchipelagoGD2/blob/main/changelog.md)\r\nAPWorld source code - https://github.com/matorblal-byte/APWorldForGDArch/tree/main/worlds\r\nAPCpp-gd source code - https://github.com/matorblal-byte/APCpp-gd\r\nSource code in in this repo if that wasnt clear already\r\nPlease report bugs thank you! \r\nPreparing to add progressive gauntlets and or map packs \r\n## Things to consider\r\n**Backup your save data before going into archipelago mode to be safe!!**\r\nSpeed modifers weights are a little flawed 2.5x is like 1.4x for some reason whoops\r\nCurrent release include debug buttons ignore them click the silver one\r\nCould softlock - APWorld generation could make it impossible\r\nDeathlink is untested\r\nMacOS untested (what i mean by this is with wine and other stuffs that left you run windows applications)\r\nIf you disable the coins checkbox, it'll also disable randomized portals \r\n## How to import\r\nGet geode (i assume you have it)\r\nDownload both files, run the apworld to install it \r\nDrag the .geode into the mods folder (Right click in GD and press open local files, geode, mods, then drag it) \r\nOn the arch client, generate template options, options creator, generate, then host it\r\nConnect to Archipelago with the top right button when you go into GD! \r\nShould now be in",
      "download_url": "https://github.com/matorblal-byte/ArchipelagoGD2/releases/download/v1.0.0-alpha.10/geometrydash.apworld",
      "has_manifest": false,
      "hash_sha256": "e7bd3e99b181de89cd6c5791f79903e845b02c7321774b7e8c60b8e686981b31",
      "html_url": "https://github.com/matorblal-byte/ArchipelagoGD2/releases/tag/v1.0.0-alpha.10",
      "size": 6312,
      "source_url": "https://api.github.com/repos/matorblal-byte/ArchipelagoGD2",
      "tag": "v1.0.0-alpha.10",
      "title": "v1.0.0-alpha.10",
      "version_simple": "1.0.0",
      "world_version": "1.0.0a10"
    },
    "v1.0.0-alpha.11": {
      "created_at": "2026-04-13T20:40:34Z",
      "description": "Bugfix 8 update!\r\nChangelogs in [changelogs.md](https://github.com/matorblal-byte/ArchipelagoGD2/blob/main/changelog.md)\r\nAPWorld source code - https://github.com/matorblal-byte/APWorldForGDArch/tree/main/worlds\r\nAPCpp-gd source code - https://github.com/matorblal-byte/APCpp-gd\r\nSource code in in this repo if that wasnt clear already\r\nPlease report bugs thank you! \r\nPreparing to add progressive gauntlets and or map packs \r\n## Things to consider\r\n**Backup your save data before going into archipelago mode to be safe!!**\r\nSpeed modifers weights are a little flawed 2.5x is like 1.4x for some reason whoops\r\nCould softlock - APWorld generation could make it impossible\r\nDeathlink is untested\r\nMacOS untested (what i mean by this is with wine and other stuffs that left you run windows applications)\r\nIf you disable the coins checkbox, it'll also disable randomized portals \r\n## How to import\r\nGet geode (i assume you have it)\r\nDownload both files, run the apworld to install it \r\nDrag the .geode into the mods folder (Right click in GD and press open local files, geode, mods, then drag it) \r\nOn the arch client, generate template options, options creator, generate, then host it\r\nConnect to Archipelago with the top right button when you go into GD! \r\nShould now be in",
      "download_url": "https://github.com/matorblal-byte/ArchipelagoGD2/releases/download/v1.0.0-alpha.11/geometrydash.apworld",
      "has_manifest": false,
      "hash_sha256": "e7bd3e99b181de89cd6c5791f79903e845b02c7321774b7e8c60b8e686981b31",
      "html_url": "https://github.com/matorblal-byte/ArchipelagoGD2/releases/tag/v1.0.0-alpha.11",
      "size": 6312,
      "source_url": "https://api.github.com/repos/matorblal-byte/ArchipelagoGD2",
      "tag": "v1.0.0-alpha.11",
      "title": "v1.0.0-alpha.11",
      "version_simple": "1.0.0",
      "world_version": "1.0.0a11"
    },
    "v1.0.0-alpha.12-pr": {
      "created_at": "2026-04-26T03:07:36Z",
      "description": "Making a prerelease for an Alpha is Crazy (before i do some testing)\r\n- Revamp APWorld (fixes unknown location Finally)\r\n- Fix crash by reentering the shop once you bought an item\r\n- Reduce shop items price\r\nUpgrade to archipelago v0.6.7",
      "download_url": "https://github.com/matorblal-byte/ArchipelagoGD2/releases/download/v1.0.0-alpha.12-pr/geometrydash.apworld",
      "has_manifest": true,
      "hash_sha256": "c656c732d4d730fd20cfcebe0f6bb84b20720a8178f3a4814f4bca5669410334",
      "html_url": "https://github.com/matorblal-byte/ArchipelagoGD2/releases/tag/v1.0.0-alpha.12-pr",
      "minimum_ap_version": "0.6.7",
      "prerelease": true,
      "size": 9816,
      "source_url": "https://api.github.com/repos/matorblal-byte/ArchipelagoGD2",
      "tag": "v1.0.0-alpha.12-pr",
      "title": "v1.0.0-alpha.12-pr",
      "version_simple": "1.0.0",
      "world_version": "1.0.0a12"
    },
    "v1.0.0-alpha.2": {
      "created_at": "2026-03-30T01:23:33Z",
      "description": "**Small warning that the APWorld is incredibly buggy and the whole thing may be unstable!! You may have to regenerate multiple times**\r\nChangelogs in [changelogs.md](https://github.com/matorblal-byte/ArchipelagoGD2/blob/main/changelog.md)\r\nAPWorld source code - https://github.com/matorblal-byte/APWorldForGDArch/tree/main/worlds\r\nAPCpp-gd source code - https://github.com/matorblal-byte/APCpp-gd\r\nSource code in in this repo if that wasnt clear already\r\nPlease report bugs thank you! \r\nPreparing to add progressive gauntlets and or map packs \r\n## Things to consider\r\n**Backup your save data before going into archipelago mode to be safe!!**\r\nSpeed modifers weights are a little flawed 2.5x is like 1.4x for some reason whoops\r\nCurrent release include debug buttons ignore them click the silver one\r\nCould softlock - APWorld generation could make it impossible\r\nDeathlink is untested\r\nMacOS and Linux untested (what i mean by this is with wine and other stuffs that left you run windows applications)\r\nIf you disable the coins checkbox, it'll also disable randomized portals \r\n## How to import\r\nGet geode (i assume you have it)\r\nDownload both files, run the apworld to install it \r\nDrag the .geode into the mods folder (Right click in GD and press open local files, geode, mods, then drag it) \r\nOn the arch client, generate template options, options creator, generate, then host it\r\nConnect to Archipelago with the top right button when you go into GD! \r\nShould now be in",
      "download_url": "https://github.com/matorblal-byte/ArchipelagoGD2/releases/download/v1.0.0-alpha.2/geometrydash.apworld",
      "has_manifest": false,
      "hash_sha256": "7769fad36694294dbd9adf0d4200edcdc81a6ae60e0a327d4eccf493402f74c0",
      "html_url": "https://github.com/matorblal-byte/ArchipelagoGD2/releases/tag/v1.0.0-alpha.2",
      "size": 6230,
      "source_url": "https://api.github.com/repos/matorblal-byte/ArchipelagoGD2",
      "tag": "v1.0.0-alpha.2",
      "title": "",
      "version_simple": "1.0.0",
      "world_version": "1.0.0a2"
    },
    "v1.0.0-alpha.3": {
      "created_at": "2026-03-31T04:09:06Z",
      "description": "Bugfix update!\r\n**Small warning that the APWorld is incredibly buggy and the whole thing may be unstable!! You may have to regenerate multiple times**\r\nChangelogs in [changelogs.md](https://github.com/matorblal-byte/ArchipelagoGD2/blob/main/changelog.md)\r\nAPWorld source code - https://github.com/matorblal-byte/APWorldForGDArch/tree/main/worlds\r\nAPCpp-gd source code - https://github.com/matorblal-byte/APCpp-gd\r\nSource code in in this repo if that wasnt clear already\r\nPlease report bugs thank you! \r\nPreparing to add progressive gauntlets and or map packs \r\n## Things to consider\r\n**Backup your save data before going into archipelago mode to be safe!!**\r\nSpeed modifers weights are a little flawed 2.5x is like 1.4x for some reason whoops\r\nCurrent release include debug buttons ignore them click the silver one\r\nCould softlock - APWorld generation could make it impossible\r\nDeathlink is untested\r\nMacOS and Linux untested (what i mean by this is with wine and other stuffs that left you run windows applications)\r\nIf you disable the coins checkbox, it'll also disable randomized portals \r\n## How to import\r\nGet geode (i assume you have it)\r\nDownload both files, run the apworld to install it \r\nDrag the .geode into the mods folder (Right click in GD and press open local files, geode, mods, then drag it) \r\nOn the arch client, generate template options, options creator, generate, then host it\r\nConnect to Archipelago with the top right button when you go into GD! \r\nShould now be in",
      "download_url": "https://github.com/matorblal-byte/ArchipelagoGD2/releases/download/v1.0.0-alpha.3/geometrydash.apworld",
      "has_manifest": false,
      "hash_sha256": "7769fad36694294dbd9adf0d4200edcdc81a6ae60e0a327d4eccf493402f74c0",
      "html_url": "https://github.com/matorblal-byte/ArchipelagoGD2/releases/tag/v1.0.0-alpha.3",
      "size": 6230,
      "source_url": "https://api.github.com/repos/matorblal-byte/ArchipelagoGD2",
      "tag": "v1.0.0-alpha.3",
      "title": "v1.0.0-alpha.3",
      "version_simple": "1.0.0",
      "world_version": "1.0.0a3"
    },
    "v1.0.0-alpha.4": {
      "created_at": "2026-04-01T17:31:58Z",
      "description": "Nice update!\r\n**The check shop buying is a little unstable and could crash at any time**\r\nChangelogs in [changelogs.md](https://github.com/matorblal-byte/ArchipelagoGD2/blob/main/changelog.md)\r\nAPWorld source code - https://github.com/matorblal-byte/APWorldForGDArch/tree/main/worlds\r\nAPCpp-gd source code - https://github.com/matorblal-byte/APCpp-gd\r\nSource code in in this repo if that wasnt clear already\r\nPlease report bugs thank you! \r\nPreparing to add progressive gauntlets and or map packs \r\n## Things to consider\r\n**Backup your save data before going into archipelago mode to be safe!!**\r\nSpeed modifers weights are a little flawed 2.5x is like 1.4x for some reason whoops\r\nCurrent release include debug buttons ignore them click the silver one\r\nCould softlock - APWorld generation could make it impossible\r\nDeathlink is untested\r\nMacOS and Linux untested (what i mean by this is with wine and other stuffs that left you run windows applications)\r\nIf you disable the coins checkbox, it'll also disable randomized portals \r\n## How to import\r\nGet geode (i assume you have it)\r\nDownload both files, run the apworld to install it \r\nDrag the .geode into the mods folder (Right click in GD and press open local files, geode, mods, then drag it) \r\nOn the arch client, generate template options, options creator, generate, then host it\r\nConnect to Archipelago with the top right button when you go into GD! \r\nShould now be in\r\n<sup><sub>[normal version](https://github.com/matorblal-byte/ArchipelagoGD2/actions/runs/23861960301)</sub></sup>",
      "download_url": "https://github.com/matorblal-byte/ArchipelagoGD2/releases/download/v1.0.0-alpha.4/geometrydash.apworld",
      "has_manifest": false,
      "hash_sha256": "e7bd3e99b181de89cd6c5791f79903e845b02c7321774b7e8c60b8e686981b31",
      "html_url": "https://github.com/matorblal-byte/ArchipelagoGD2/releases/tag/v1.0.0-alpha.4",
      "size": 6312,
      "source_url": "https://api.github.com/repos/matorblal-byte/ArchipelagoGD2",
      "tag": "v1.0.0-alpha.4",
      "title": "v1.0.0-alpha.4",
      "version_simple": "1.0.0",
      "world_version": "1.0.0a4"
    },
    "v1.0.0-alpha.5": {
      "created_at": "2026-04-05T04:12:30Z",
      "description": "i made a mistake in the release orignally so uhhh hi\r\nBugfix 2 update!\r\nChangelogs in [changelogs.md](https://github.com/matorblal-byte/ArchipelagoGD2/blob/main/changelog.md)\r\nAPWorld source code - https://github.com/matorblal-byte/APWorldForGDArch/tree/main/worlds\r\nAPCpp-gd source code - https://github.com/matorblal-byte/APCpp-gd\r\nSource code in in this repo if that wasnt clear already\r\nPlease report bugs thank you! \r\nPreparing to add progressive gauntlets and or map packs \r\n## Things to consider\r\n**Backup your save data before going into archipelago mode to be safe!!**\r\nSpeed modifers weights are a little flawed 2.5x is like 1.4x for some reason whoops\r\nCurrent release include debug buttons ignore them click the silver one\r\nCould softlock - APWorld generation could make it impossible\r\nDeathlink is untested\r\nMacOS untested (what i mean by this is with wine and other stuffs that left you run windows applications)\r\nIf you disable the coins checkbox, it'll also disable randomized portals \r\n## How to import\r\nGet geode (i assume you have it)\r\nDownload both files, run the apworld to install it \r\nDrag the .geode into the mods folder (Right click in GD and press open local files, geode, mods, then drag it) \r\nOn the arch client, generate template options, options creator, generate, then host it\r\nConnect to Archipelago with the top right button when you go into GD! \r\nShould now be in",
      "download_url": "https://github.com/matorblal-byte/ArchipelagoGD2/releases/download/v1.0.0-alpha.5/geometrydash.apworld",
      "has_manifest": false,
      "hash_sha256": "e7bd3e99b181de89cd6c5791f79903e845b02c7321774b7e8c60b8e686981b31",
      "html_url": "https://github.com/matorblal-byte/ArchipelagoGD2/releases/tag/v1.0.0-alpha.5",
      "size": 6312,
      "source_url": "https://api.github.com/repos/matorblal-byte/ArchipelagoGD2",
      "tag": "v1.0.0-alpha.5",
      "title": "v1.0.0-alpha.5",
      "version_simple": "1.0.0",
      "world_version": "1.0.0a5"
    },
    "v1.0.0-alpha.6": {
      "created_at": "2026-04-07T02:55:49Z",
      "description": "Bugfix 3 update!\r\nChangelogs in [changelogs.md](https://github.com/matorblal-byte/ArchipelagoGD2/blob/main/changelog.md)\r\nAPWorld source code - https://github.com/matorblal-byte/APWorldForGDArch/tree/main/worlds\r\nAPCpp-gd source code - https://github.com/matorblal-byte/APCpp-gd\r\nSource code in in this repo if that wasnt clear already\r\nPlease report bugs thank you! \r\nPreparing to add progressive gauntlets and or map packs \r\n## Things to consider\r\n**Backup your save data before going into archipelago mode to be safe!!**\r\nSpeed modifers weights are a little flawed 2.5x is like 1.4x for some reason whoops\r\nCurrent release include debug buttons ignore them click the silver one\r\nCould softlock - APWorld generation could make it impossible\r\nDeathlink is untested\r\nMacOS untested (what i mean by this is with wine and other stuffs that left you run windows applications)\r\nIf you disable the coins checkbox, it'll also disable randomized portals \r\n## How to import\r\nGet geode (i assume you have it)\r\nDownload both files, run the apworld to install it \r\nDrag the .geode into the mods folder (Right click in GD and press open local files, geode, mods, then drag it) \r\nOn the arch client, generate template options, options creator, generate, then host it\r\nConnect to Archipelago with the top right button when you go into GD! \r\nShould now be in",
      "download_url": "https://github.com/matorblal-byte/ArchipelagoGD2/releases/download/v1.0.0-alpha.6/geometrydash.apworld",
      "has_manifest": false,
      "hash_sha256": "e7bd3e99b181de89cd6c5791f79903e845b02c7321774b7e8c60b8e686981b31",
      "html_url": "https://github.com/matorblal-byte/ArchipelagoGD2/releases/tag/v1.0.0-alpha.6",
      "size": 6312,
      "source_url": "https://api.github.com/repos/matorblal-byte/ArchipelagoGD2",
      "tag": "v1.0.0-alpha.6",
      "title": "v1.0.0-alpha.6",
      "version_simple": "1.0.0",
      "world_version": "1.0.0a6"
    },
    "v1.0.0-alpha.7": {
      "created_at": "2026-04-08T02:00:35Z",
      "description": "Bugfix 4 update!\r\nHopefully fixes the c++ exception which I was not able to replicate!\r\nChangelogs in [changelogs.md](https://github.com/matorblal-byte/ArchipelagoGD2/blob/main/changelog.md)\r\nAPWorld source code - https://github.com/matorblal-byte/APWorldForGDArch/tree/main/worlds\r\nAPCpp-gd source code - https://github.com/matorblal-byte/APCpp-gd\r\nSource code in in this repo if that wasnt clear already\r\nPlease report bugs thank you! \r\nPreparing to add progressive gauntlets and or map packs \r\n## Things to consider\r\n**Backup your save data before going into archipelago mode to be safe!!**\r\nSpeed modifers weights are a little flawed 2.5x is like 1.4x for some reason whoops\r\nCould softlock - APWorld generation could make it impossible\r\nDeathlink is untested\r\nMacOS untested (what i mean by this is with wine and other stuffs that left you run windows applications)\r\nIf you disable the coins checkbox, it'll also disable randomized portals \r\n## How to import\r\nGet geode (i assume you have it)\r\nDownload both files, run the apworld to install it \r\nDrag the .geode into the mods folder (Right click in GD and press open local files, geode, mods, then drag it) \r\nOn the arch client, generate template options, options creator, generate, then host it\r\nConnect to Archipelago with the top right button when you go into GD! \r\nShould now be in",
      "download_url": "https://github.com/matorblal-byte/ArchipelagoGD2/releases/download/v1.0.0-alpha.7/geometrydash.apworld",
      "has_manifest": false,
      "hash_sha256": "e7bd3e99b181de89cd6c5791f79903e845b02c7321774b7e8c60b8e686981b31",
      "html_url": "https://github.com/matorblal-byte/ArchipelagoGD2/releases/tag/v1.0.0-alpha.7",
      "size": 6312,
      "source_url": "https://api.github.com/repos/matorblal-byte/ArchipelagoGD2",
      "tag": "v1.0.0-alpha.7",
      "title": "v1.0.0-alpha.7",
      "version_simple": "1.0.0",
      "world_version": "1.0.0a7"
    },
    "v1.0.0-alpha.8": {
      "created_at": "2026-04-11T14:18:46Z",
      "description": "Bugfix 5 update!\r\nChangelogs in [changelogs.md](https://github.com/matorblal-byte/ArchipelagoGD2/blob/main/changelog.md)\r\nAPWorld source code - https://github.com/matorblal-byte/APWorldForGDArch/tree/main/worlds\r\nAPCpp-gd source code - https://github.com/matorblal-byte/APCpp-gd\r\nSource code in in this repo if that wasnt clear already\r\nPlease report bugs thank you! \r\nPreparing to add progressive gauntlets and or map packs \r\n## Things to consider\r\n**Backup your save data before going into archipelago mode to be safe!!**\r\nSpeed modifers weights are a little flawed 2.5x is like 1.4x for some reason whoops\r\nCurrent release include debug buttons ignore them click the silver one\r\nCould softlock - APWorld generation could make it impossible\r\nDeathlink is untested\r\nMacOS untested (what i mean by this is with wine and other stuffs that left you run windows applications)\r\nIf you disable the coins checkbox, it'll also disable randomized portals \r\n## How to import\r\nGet geode (i assume you have it)\r\nDownload both files, run the apworld to install it \r\nDrag the .geode into the mods folder (Right click in GD and press open local files, geode, mods, then drag it) \r\nOn the arch client, generate template options, options creator, generate, then host it\r\nConnect to Archipelago with the top right button when you go into GD! \r\nShould now be in",
      "download_url": "https://github.com/matorblal-byte/ArchipelagoGD2/releases/download/v1.0.0-alpha.8/geometrydash.apworld",
      "has_manifest": false,
      "hash_sha256": "e7bd3e99b181de89cd6c5791f79903e845b02c7321774b7e8c60b8e686981b31",
      "html_url": "https://github.com/matorblal-byte/ArchipelagoGD2/releases/tag/v1.0.0-alpha.8",
      "size": 6312,
      "source_url": "https://api.github.com/repos/matorblal-byte/ArchipelagoGD2",
      "tag": "v1.0.0-alpha.8",
      "title": "v1.0.0-alpha.8",
      "version_simple": "1.0.0",
      "world_version": "1.0.0a8"
    },
    "v1.0.0-alpha.8.5": {
      "created_at": "2026-04-11T23:30:45Z",
      "description": "This release is a bridge between 8 and 9 to fix a critical bug with data saving therefore i will not write anything here",
      "download_url": "https://github.com/matorblal-byte/ArchipelagoGD2/releases/download/v1.0.0-alpha.8.5/geometrydash.apworld",
      "has_manifest": false,
      "hash_sha256": "e7bd3e99b181de89cd6c5791f79903e845b02c7321774b7e8c60b8e686981b31",
      "html_url": "https://github.com/matorblal-byte/ArchipelagoGD2/releases/tag/v1.0.0-alpha.8.5",
      "size": 6312,
      "source_url": "https://api.github.com/repos/matorblal-byte/ArchipelagoGD2",
      "tag": "v1.0.0-alpha.8.5",
      "title": "v1.0.0-alpha.8.5",
      "version_simple": "1.0.0",
      "world_version": "1.0.0a8"
    },
    "v1.0.0-alpha.9": {
      "created_at": "2026-04-12T17:48:45Z",
      "description": "Bugfix 6 update! (Oh my god Bro)\r\nChangelogs in [changelogs.md](https://github.com/matorblal-byte/ArchipelagoGD2/blob/main/changelog.md)\r\nAPWorld source code - https://github.com/matorblal-byte/APWorldForGDArch/tree/main/worlds\r\nAPCpp-gd source code - https://github.com/matorblal-byte/APCpp-gd\r\nSource code in in this repo if that wasnt clear already\r\nPlease report bugs thank you! \r\nPreparing to add progressive gauntlets and or map packs \r\n## Things to consider\r\n**Backup your save data before going into archipelago mode to be safe!!**\r\nSpeed modifers weights are a little flawed 2.5x is like 1.4x for some reason whoops\r\nCurrent release include debug buttons ignore them click the silver one\r\nCould softlock - APWorld generation could make it impossible\r\nDeathlink is untested\r\nMacOS untested (what i mean by this is with wine and other stuffs that left you run windows applications)\r\nIf you disable the coins checkbox, it'll also disable randomized portals \r\n## How to import\r\nGet geode (i assume you have it)\r\nDownload both files, run the apworld to install it \r\nDrag the .geode into the mods folder (Right click in GD and press open local files, geode, mods, then drag it) \r\nOn the arch client, generate template options, options creator, generate, then host it\r\nConnect to Archipelago with the top right button when you go into GD! \r\nShould now be in",
      "download_url": "https://github.com/matorblal-byte/ArchipelagoGD2/releases/download/v1.0.0-alpha.9/geometrydash.apworld",
      "has_manifest": false,
      "hash_sha256": "e7bd3e99b181de89cd6c5791f79903e845b02c7321774b7e8c60b8e686981b31",
      "html_url": "https://github.com/matorblal-byte/ArchipelagoGD2/releases/tag/v1.0.0-alpha.9",
      "size": 6312,
      "source_url": "https://api.github.com/repos/matorblal-byte/ArchipelagoGD2",
      "tag": "v1.0.0-alpha.9",
      "title": "v1.0.0-alpha.9",
      "version_simple": "1.0.0",
      "world_version": "1.0.0a9"
    }
  }
}
