{
  "description": "Portal 2 is a first person puzzle adventure where you shoot solve test chambers using portal mechanics and other map specific items",
  "game": "Portal 2",
  "github": "https://github.com/GlassToadstool/Archipelago",
  "license": null,
  "versions": {
    "0.1": {
      "created_at": "2025-12-06T21:46:10Z",
      "download_url": "https://github.com/GlassToadstool/Archipelago/releases/download/0.1/portal2.apworld",
      "has_manifest": false,
      "hash_sha256": "8b580fd2dad9c86b84a726129b7d47cdab58fdc06f33591c11cfff75abe80b02",
      "prerelease": true,
      "size": 61750,
      "source_url": "https://api.github.com/repos/GlassToadstool/Archipelago",
      "tag": "0.1",
      "title": "Portal 2 Archipelago v0.1",
      "version_simple": "0.1",
      "world_version": "0.1"
    },
    "0.2": {
      "created_at": "2025-12-14T16:28:55Z",
      "download_url": "https://github.com/GlassToadstool/Archipelago/releases/download/0.2/portal2.apworld",
      "has_manifest": false,
      "hash_sha256": "31f5cb2ef39732c81600266e98816b366cff50f9680fe31d2255acbe5103901e",
      "prerelease": true,
      "size": 78364,
      "source_url": "https://api.github.com/repos/GlassToadstool/Archipelago",
      "tag": "0.2",
      "title": "Portal 2 Archipelago v0.2",
      "version_simple": "0.2",
      "world_version": "0.2"
    },
    "0.3": {
      "created_at": "2026-01-13T14:31:20Z",
      "download_url": "https://github.com/GlassToadstool/Archipelago/releases/download/0.3/portal2.apworld",
      "has_manifest": false,
      "hash_sha256": "b5830df43b863556283d588da78af6c1dd6d29b88d2629de4ca6869399594a14",
      "size": 82921,
      "source_url": "https://api.github.com/repos/GlassToadstool/Archipelago",
      "tag": "0.3",
      "title": "Portal 2 Archipelago v0.3",
      "version_simple": "0.3",
      "world_version": "0.3"
    },
    "0.3.1": {
      "created_at": "2026-01-22T14:53:55Z",
      "download_url": "https://github.com/GlassToadstool/Archipelago/releases/download/0.3.1/portal2.apworld",
      "has_manifest": false,
      "hash_sha256": "87b5896c9cde26557354d610c858007e2250fe8e440105dee9f8890fbfceb3f5",
      "size": 85168,
      "source_url": "https://api.github.com/repos/GlassToadstool/Archipelago",
      "tag": "0.3.1",
      "title": "Portal 2 Archipelago v0.3.1",
      "version_simple": "0.3.1",
      "world_version": "0.3.1"
    },
    "0.3.2": {
      "created_at": "2026-01-22T18:17:12Z",
      "download_url": "https://github.com/GlassToadstool/Archipelago/releases/download/0.3.2/portal2.apworld",
      "has_manifest": true,
      "hash_sha256": "1668142915ba5d9460507a4e1391631b50095691aee97a8eff4308dfd42464a8",
      "minimum_ap_version": "0.6.3",
      "size": 36624,
      "source_url": "https://api.github.com/repos/GlassToadstool/Archipelago",
      "tag": "0.3.2",
      "title": "Portal 2 Archipelago v0.3.2",
      "version_simple": "0.3.2",
      "world_version": "0.3.2"
    },
    "0.3.3": {
      "created_at": "2026-01-27T19:25:12Z",
      "download_url": "https://github.com/GlassToadstool/Archipelago/releases/download/0.3.3/portal2.apworld",
      "has_manifest": true,
      "hash_sha256": "9369111130a1ed42608b9eeaf5241503dd67db195a338bbee928e80c940af56a",
      "minimum_ap_version": "0.6.3",
      "size": 36682,
      "source_url": "https://api.github.com/repos/GlassToadstool/Archipelago",
      "tag": "0.3.3",
      "title": "Portal 2 Archipelago v0.3.3",
      "version_simple": "0.3.3",
      "world_version": "0.3.3"
    },
    "0.3r2": {
      "created_at": "2026-01-13T14:31:20Z",
      "download_url": "https://github.com/GlassToadstool/Archipelago/releases/download/0.3/portal2.apworld",
      "has_manifest": false,
      "hash_sha256": "1cd11cbed052a39a9d7998a5be8cbe7534e1b3c6cb530c093bb202d7993935b2",
      "size": 83042,
      "source_url": "https://api.github.com/repos/GlassToadstool/Archipelago",
      "tag": "0.3r2",
      "title": "Portal 2 Archipelago v0.3",
      "version_simple": "0.3",
      "world_version": "0.3.post2"
    }
  }
}
