{
  "authors": [
    "Automagic, ThisGuyHere"
  ],
  "game": "R.E.P.O",
  "github": "https://github.com/Automagic00/R.E.P.O.-Archipelago-Client-Mod",
  "manifest_fields": [],
  "versions": {
    "0.0.1": {
      "created_at": "2025-05-02T04:42:54Z",
      "description": "First playable build of the REPO Archipelago",
      "download_url": "https://github.com/Automagic00/R.E.P.O.-Archipelago-Client-Mod/releases/download/0.0.1/repo.apworld",
      "has_manifest": false,
      "hash_sha256": "90c4c40dc8664ffc03d92e7b5e1b34a1b5fe0017471d31c96c3eca9887fa04af",
      "html_url": "https://github.com/Automagic00/R.E.P.O.-Archipelago-Client-Mod/releases/tag/0.0.1",
      "size": 43094,
      "source_url": "https://api.github.com/repos/Automagic00/R.E.P.O.-Archipelago-Client-Mod",
      "tag": "0.0.1",
      "title": "REPO Release 0.0.1",
      "version_simple": "0.0.1",
      "world_version": "0.0.1"
    },
    "0.0.2": {
      "created_at": "2025-05-06T22:56:14Z",
      "description": "## Additions\r\n - Weighted Item Upgrades. Item pool is more likely to be populated by useful upgrades.\r\n - Option for Total Shop Upgrades. Allows the player to control how many location checks exist in shops.\r\n - Option for Shop Upgrade Logic. Allows the player to control how many upgrades in the shop can contain progression items.\r\n \r\n ## Fixes\r\n - Clients now see the what shop items will send to the multiworld.\r\n - Pelly size was reduced so that they won't get stuck in small spaces.\r\n - Strength Upgrades can now be randomly added to the item pool beyond the 3 in logic.",
      "download_url": "https://github.com/Automagic00/R.E.P.O.-Archipelago-Client-Mod/releases/download/0.0.2/repo.apworld",
      "has_manifest": false,
      "hash_sha256": "1965b169e677fbdccfa1710bde7c82693b216f95693d2ca39bac0047ed9bdcb6",
      "html_url": "https://github.com/Automagic00/R.E.P.O.-Archipelago-Client-Mod/releases/tag/0.0.2",
      "size": 44132,
      "source_url": "https://api.github.com/repos/Automagic00/R.E.P.O.-Archipelago-Client-Mod",
      "tag": "0.0.2",
      "title": "REPO Patch 0.0.2",
      "version_simple": "0.0.2",
      "world_version": "0.0.2"
    },
    "0.0.3": {
      "created_at": "2025-05-07T04:39:03Z",
      "description": "## Fixes\r\n- Quotas no longer cost $1",
      "download_url": "https://github.com/Automagic00/R.E.P.O.-Archipelago-Client-Mod/releases/download/0.0.3/repo.apworld",
      "has_manifest": false,
      "hash_sha256": "1965b169e677fbdccfa1710bde7c82693b216f95693d2ca39bac0047ed9bdcb6",
      "html_url": "https://github.com/Automagic00/R.E.P.O.-Archipelago-Client-Mod/releases/tag/0.0.3",
      "size": 44132,
      "source_url": "https://api.github.com/repos/Automagic00/R.E.P.O.-Archipelago-Client-Mod",
      "tag": "0.0.3",
      "title": "REPO Hotfix 0.0.3",
      "version_simple": "0.0.3",
      "world_version": "0.0.3"
    },
    "0.1.0": {
      "created_at": "2025-05-17T01:12:10Z",
      "description": "# R.E.P.O. Archipelago v0.1.0\r\n\r\n## Features\r\n### Monster Hunt\r\n- Monster soul orbs are now checks\r\n- New option that lets players choose if extracting all soul orbs is required for completion\r\n\r\n### Valuable Hunt\r\n- Each unique valuable is a check\r\n- New option that lets players choose if extracting all valuables is required for completion\r\n\r\n### Progressive Shop Stock item\r\n- Added Progressive Shop Stock to the item pool\r\n- Receiving a Progressive Shop Stock will unlock more Archipelago Items in the Shop\r\n- New option that lets players choose how many Archipelago Items are unlocked with each Progressive Shop Stock\r\n\r\n### Pelly Spawn Option\r\n- New option that allows players to prevent non-goal-required Pellys from spawning\r\n\r\n### Item Weight Option\r\n- New option that allows players to choose how upgrade items are weighted in the item pool\r\n\r\n## Fixes\r\n- McJannek Station and Swiftbroom Academy Pellys no longer send out the wrong location ID's\r\n- Pelly Hunt Goal should be properly functional now\r\n- Generation no longer creates more items than locations\r\n- Fixed many generation errors that prevented generation from completing",
      "download_url": "https://github.com/Automagic00/R.E.P.O.-Archipelago-Client-Mod/releases/download/0.1.0/repo.apworld",
      "has_manifest": false,
      "hash_sha256": "ca90e04f58d0d0496d8997dbbe1192aadc36aaa9f47030b1233ce3123ace6da9",
      "html_url": "https://github.com/Automagic00/R.E.P.O.-Archipelago-Client-Mod/releases/tag/0.1.0",
      "size": 38596,
      "source_url": "https://api.github.com/repos/Automagic00/R.E.P.O.-Archipelago-Client-Mod",
      "tag": "0.1.0",
      "title": "REPO Release 0.1.0",
      "version_simple": "0.1.0",
      "world_version": "0.1.0"
    },
    "0.1.1": {
      "created_at": "2025-05-21T19:53:31Z",
      "description": "## Fixes\r\n - Fixed Cube of Knowledge and Dumgolfs Staff not sending location",
      "download_url": "https://github.com/Automagic00/R.E.P.O.-Archipelago-Client-Mod/releases/download/0.1.1/repo.apworld",
      "has_manifest": false,
      "hash_sha256": "ca90e04f58d0d0496d8997dbbe1192aadc36aaa9f47030b1233ce3123ace6da9",
      "html_url": "https://github.com/Automagic00/R.E.P.O.-Archipelago-Client-Mod/releases/tag/0.1.1",
      "size": 38596,
      "source_url": "https://api.github.com/repos/Automagic00/R.E.P.O.-Archipelago-Client-Mod",
      "tag": "0.1.1",
      "title": "REPO Hotfix 0.1.1",
      "version_simple": "0.1.1",
      "world_version": "0.1.1"
    },
    "0.1.2": {
      "created_at": "2025-05-22T04:54:59Z",
      "description": "## Fixes\r\n- Valuable Hunt not checking goal conditions correctly\r\n- Monster Souls not sending checks",
      "download_url": "https://github.com/Automagic00/R.E.P.O.-Archipelago-Client-Mod/releases/download/0.1.2/repo.apworld",
      "has_manifest": false,
      "hash_sha256": "ca90e04f58d0d0496d8997dbbe1192aadc36aaa9f47030b1233ce3123ace6da9",
      "html_url": "https://github.com/Automagic00/R.E.P.O.-Archipelago-Client-Mod/releases/tag/0.1.2",
      "size": 38596,
      "source_url": "https://api.github.com/repos/Automagic00/R.E.P.O.-Archipelago-Client-Mod",
      "tag": "0.1.2",
      "title": "REPO Hotfix 0.1.2",
      "version_simple": "0.1.2",
      "world_version": "0.1.2"
    },
    "0.1.3": {
      "created_at": "2025-05-22T18:26:19Z",
      "description": "## Fixes\r\n- Progressive Shop Stock will update properly during runs, not just between runs.",
      "download_url": "https://github.com/Automagic00/R.E.P.O.-Archipelago-Client-Mod/releases/download/0.1.3/repo.apworld",
      "has_manifest": false,
      "hash_sha256": "ca90e04f58d0d0496d8997dbbe1192aadc36aaa9f47030b1233ce3123ace6da9",
      "html_url": "https://github.com/Automagic00/R.E.P.O.-Archipelago-Client-Mod/releases/tag/0.1.3",
      "size": 38596,
      "source_url": "https://api.github.com/repos/Automagic00/R.E.P.O.-Archipelago-Client-Mod",
      "tag": "0.1.3",
      "title": "REPO Hotfix 0.1.3",
      "version_simple": "0.1.3",
      "world_version": "0.1.3"
    },
    "0.1.4": {
      "created_at": "2025-05-22T22:05:48Z",
      "description": "## Fixes\r\n - Fixed level selector sometimes not detecting levels the player has received\r\n - Fixed valuables sometimes not sending checks",
      "download_url": "https://github.com/Automagic00/R.E.P.O.-Archipelago-Client-Mod/releases/download/0.1.4/repo.apworld",
      "has_manifest": false,
      "hash_sha256": "ca90e04f58d0d0496d8997dbbe1192aadc36aaa9f47030b1233ce3123ace6da9",
      "html_url": "https://github.com/Automagic00/R.E.P.O.-Archipelago-Client-Mod/releases/tag/0.1.4",
      "size": 38596,
      "source_url": "https://api.github.com/repos/Automagic00/R.E.P.O.-Archipelago-Client-Mod",
      "tag": "0.1.4",
      "title": "REPO Hotfix 0.1.4",
      "version_simple": "0.1.4",
      "world_version": "0.1.4"
    },
    "0.1.5": {
      "created_at": "2025-06-03T20:18:11Z",
      "description": "## Fixes\r\n- Radio, TV, and Ship in a Bottle valuables are now logically located in Headman Manor\r\n- Progressive Shop Stock should update and populate the shop correctly now",
      "download_url": "https://github.com/Automagic00/R.E.P.O.-Archipelago-Client-Mod/releases/download/0.1.5/repo.apworld",
      "has_manifest": false,
      "hash_sha256": "04283445e1ecba5b1b9f9fcab489a5d786cd707e8d02341a3df7d1f6f3c77863",
      "html_url": "https://github.com/Automagic00/R.E.P.O.-Archipelago-Client-Mod/releases/tag/0.1.5",
      "size": 38565,
      "source_url": "https://api.github.com/repos/Automagic00/R.E.P.O.-Archipelago-Client-Mod",
      "tag": "0.1.5",
      "title": "REPO Hotfix 0.1.5",
      "version_simple": "0.1.5",
      "world_version": "0.1.5"
    },
    "0.2.0": {
      "created_at": "2025-06-26T20:42:04Z",
      "description": "## Features\r\n- Added compatibility for R.E.P.O. version 0.2.0\r\n  - Includes museum level and new valuables.\r\n- Added descriptive text displaying AP-specific information about held souls or valuables.\r\n  - Displays \"Extracted\" or \"Not Extracted\" if `monster_hunt` or `valuable_hunt` were set to true in the player's options file.\r\n  - Displays the outgoing item the soul or valuable would send to another player.\r\n  - Text uses diverging colors that are designed to be color-blind friendly.\r\n- Archipelago messages to the truck screen.\r\n  - Displays the AP completion status to the truck screen of the host (levels completed,pellys collected, etc.)\r\n  - Displays AP server messages to the truck screen (including chat messages from other players).\r\n- Added unlock items in the multiworld for shop items to start appearing in the shop.\r\n- Added Combat Logic option that determines what items should be unlocked for the player to do combat.\r\n- Updated the UI for the Archipelago Connection Menu.\r\n\r\n## Fixes\r\n- Items and Goal locations should now be synced with the server, preventing issues of AP Shop items that don't send anything and Pellys not properly allowing a player to goal.\r\n- Client will now notify a player if they were disconnected from the AP server and attempt to reconnect.\r\n- Fixed an issue that would prevent pellys from spawning sometimes.\r\n- Fixed an issue that caused the game to lag during extraction.\r\n- Fixed an issue that caused the game to lag when connecting to the AP server.\r\n- Item received notifications now display in sequence if multiple are sent in a short period.\r\n\r\nBig shout out to Lokno Ketchup for their contributions to adding compatibility for the 0.2.0 Update and multiple QoL features.",
      "download_url": "https://github.com/Automagic00/R.E.P.O.-Archipelago-Client-Mod/releases/download/0.2.0/repo.apworld",
      "has_manifest": false,
      "hash_sha256": "7d2ee1e9d12c09853af80da072a65dd74bcb3688ce97259f6bfa6539f3be66de",
      "html_url": "https://github.com/Automagic00/R.E.P.O.-Archipelago-Client-Mod/releases/tag/0.2.0",
      "size": 45372,
      "source_url": "https://api.github.com/repos/Automagic00/R.E.P.O.-Archipelago-Client-Mod",
      "tag": "0.2.0",
      "title": "REPO Update 0.2.0",
      "version_simple": "0.2.0",
      "world_version": "0.2.0"
    },
    "0.2.1": {
      "created_at": "2025-06-27T20:35:14Z",
      "description": "## Fixes\r\n- Fixed pellys not being tracked properly for the goal\r\n- Fixed energy crystals not being sent to the truck after purchase",
      "download_url": "https://github.com/Automagic00/R.E.P.O.-Archipelago-Client-Mod/releases/download/0.2.1/repo.apworld",
      "has_manifest": false,
      "hash_sha256": "7d2ee1e9d12c09853af80da072a65dd74bcb3688ce97259f6bfa6539f3be66de",
      "html_url": "https://github.com/Automagic00/R.E.P.O.-Archipelago-Client-Mod/releases/tag/0.2.1",
      "size": 45372,
      "source_url": "https://api.github.com/repos/Automagic00/R.E.P.O.-Archipelago-Client-Mod",
      "tag": "0.2.1",
      "title": "REPO Hotfix 0.2.1",
      "version_simple": "0.2.1",
      "world_version": "0.2.1"
    },
    "0.2.2": {
      "created_at": "2025-07-25T19:58:57Z",
      "description": "## Fixes\r\n- Only one Progressive Health Pack was being generated\r\n- Shop was spawning items that the player hadn't recieved yet\r\n- Potential fix for save files being corrupted during the game's photosensitivity warning, causing items to not be received",
      "download_url": "https://github.com/Automagic00/R.E.P.O.-Archipelago-Client-Mod/releases/download/0.2.2/repo.apworld",
      "has_manifest": false,
      "hash_sha256": "f30b7a77f21cf01029e46b1065b402128286807944e13dabfa6d9aff157aadd2",
      "html_url": "https://github.com/Automagic00/R.E.P.O.-Archipelago-Client-Mod/releases/tag/0.2.2",
      "size": 45374,
      "source_url": "https://api.github.com/repos/Automagic00/R.E.P.O.-Archipelago-Client-Mod",
      "tag": "0.2.2",
      "title": "REPO Hotfix 0.2.2",
      "version_simple": "0.2.2",
      "world_version": "0.2.2"
    },
    "0.2.3": {
      "created_at": "2025-07-29T21:17:54Z",
      "description": "## Fixes\r\n- Adjusts the timing of checking save files to prevent errors when connecting to the Archipelago servers.\r\n\r\nShoutouts to @Gomiken for their contribution.",
      "download_url": "https://github.com/Automagic00/R.E.P.O.-Archipelago-Client-Mod/releases/download/0.2.3/repo.apworld",
      "has_manifest": false,
      "hash_sha256": "f30b7a77f21cf01029e46b1065b402128286807944e13dabfa6d9aff157aadd2",
      "html_url": "https://github.com/Automagic00/R.E.P.O.-Archipelago-Client-Mod/releases/tag/0.2.3",
      "size": 45374,
      "source_url": "https://api.github.com/repos/Automagic00/R.E.P.O.-Archipelago-Client-Mod",
      "tag": "0.2.3",
      "title": "REPO Hotfix 0.2.3",
      "version_simple": "0.2.3",
      "world_version": "0.2.3"
    },
    "0.2.4": {
      "created_at": "2025-08-01T18:38:41Z",
      "description": "## Fixes\r\n- Actually includes the things that were supposed to be in the v0.2.3 release \ud83d\udc80",
      "download_url": "https://github.com/Automagic00/R.E.P.O.-Archipelago-Client-Mod/releases/download/0.2.4/repo.apworld",
      "has_manifest": false,
      "hash_sha256": "f30b7a77f21cf01029e46b1065b402128286807944e13dabfa6d9aff157aadd2",
      "html_url": "https://github.com/Automagic00/R.E.P.O.-Archipelago-Client-Mod/releases/tag/0.2.4",
      "size": 45374,
      "source_url": "https://api.github.com/repos/Automagic00/R.E.P.O.-Archipelago-Client-Mod",
      "tag": "0.2.4",
      "title": "REPO Hotfix 0.2.4",
      "version_simple": "0.2.4",
      "world_version": "0.2.4"
    },
    "0.3.0": {
      "created_at": "2026-01-16T00:09:27Z",
      "description": "Mod:\r\n* updated in-logic items and locations to match REPO v0.3.0 logic\r\n* changed tracking of gathered pellys to use more consistent naming and added a 'found' label for collected valuables\r\n* the store can no longer contain multiple copies of the same ap item\r\n* small corrections to item sending and processing\r\n* prevented creating and loading saves until connected\r\n* some save data is now synced with clients so they can see what checks a valuable will grant\r\n* the pelly goal now correctly requires the player to extract each pelly, even if the game it would grant an item for is already complete\r\n* added two mod config options to reduce bad luck with monster and valuable spawns\r\n* added a config option to stop multiworld messages from appearing on the truck screen\r\n\r\nApworld:\r\n* updated in-logic items and locations to match REPO v0.3.0 logic\r\n  * also added the peeper soul to logic\r\n* added a manifest to ensure compatibility with future ap versions\r\n* updated 'stun mine' item name to 'Trapzap'\r\n* removed the small/medium/large health pack items (They are meant to be filler currently do nothing. Progressive health packs are what *actually* unlock each tier of the store items.)\r\n\r\nKnown issues:\r\n* Upgrade items are not restored when the player gets a game over. This isn't a major issue because the save file gets deleted anyway, so they can just create a new one.\r\n* In multiplayer, non-host players may see frequent warnings in their log about not being connected to the multiworld. These warnings can be ignored.\r\n* In multiplayer, monster souls do not display the correct monster name for clients.\r\n",
      "download_url": "https://github.com/Automagic00/R.E.P.O.-Archipelago-Client-Mod/releases/download/0.3.0/repo.apworld",
      "has_manifest": true,
      "hash_sha256": "3621a13dc5baa62c8a45d41165ebd2e91e202ae6f7972bb08b168163cc1a56d3",
      "html_url": "https://github.com/Automagic00/R.E.P.O.-Archipelago-Client-Mod/releases/tag/0.3.0",
      "size": 18085,
      "source_url": "https://api.github.com/repos/Automagic00/R.E.P.O.-Archipelago-Client-Mod",
      "tag": "0.3.0",
      "title": "REPO Update 0.3.0",
      "version_simple": "0.3.0",
      "world_version": "0.3.0"
    },
    "0.3.1": {
      "created_at": "2026-03-08T20:06:13Z",
      "description": "Mod:\r\n* upgrades are once again re-granted after death\r\n* clients now see monster soul names correctly\r\n* progress syncing improvements and fixed a race condition that occurred when syncing data with the multiworld at the end of a level\r\n\r\nThis release does not make any changes to the apworld. ",
      "download_url": "https://github.com/Automagic00/R.E.P.O.-Archipelago-Client-Mod/releases/download/0.3.1/repo.apworld",
      "has_manifest": true,
      "hash_sha256": "3621a13dc5baa62c8a45d41165ebd2e91e202ae6f7972bb08b168163cc1a56d3",
      "html_url": "https://github.com/Automagic00/R.E.P.O.-Archipelago-Client-Mod/releases/tag/0.3.1",
      "size": 18085,
      "source_url": "https://api.github.com/repos/Automagic00/R.E.P.O.-Archipelago-Client-Mod",
      "tag": "0.3.1",
      "title": "REPO Hotfix 0.3.1",
      "version_simple": "0.3.0",
      "world_version": "0.3.0"
    },
    "0.4.0": {
      "created_at": "2026-04-20T22:40:50Z",
      "description": "**This update contains breaking changes and is not compatible with previous multiworlds**\r\n\r\nMod: \r\n* truck screen now displays pellys collected and number of valuables gathered for the current level\r\n* level selection changes\r\n  * The next level is now chosen based on how many valuables are left to collect in each unlocked level\r\n  * Levels with less valuables collected are more likely to be picked\r\n* connection info is now preserved in the mod config\r\n* upgrade spawning improvements\r\n  * added space for 96 additional upgrades on the truck's side shelf, bringing the total to 112\r\n  * the spawning itself is still handled by the vanilla method\r\n  * allowed up to 20 of each upgrade to spawn in the truck at once\r\n* changes to shop item pools\r\n  * moved secret shop items to the normal shop pool\r\n  * the secret pool now acts as a \"black market\", where every unlocked shop item appears in the pool and locked items have a 10% chance to appear in the pool\r\n* changed how upgrade usage is tracked per-save\r\n* truck screen optimizations\r\n  * messages are now dequeued in batches every 0.25 seconds\r\n  * if more than 200 messages are in the queue, additional messages that do not mention the current player will be dropped\r\n* you no longer need to hide the BepInEx manager object!!!\r\n* fixed a timing issue that prevented clients from seeing the names of AP shop items\r\n* upgrades (and AP items) now spawn in the shop regardless of how many upgrades are in the truck\r\n\r\nApworld:\r\n* added death link\r\n* added 4 traps\r\n* added small health packs as a filler item\r\n* changed pelly goal to require a user-chosen number of pellys\r\n* fixed some incorrect item names\r\n* made changes to monster killing logic\r\n  * stun items now have their own item group\r\n  * each monster now requires a minimum strength to pick up, instead of all monsters requiring 13 strength\r\n  * the peeper soul can't logically be obtained with strength upgrades\r\n  * the Elsa and Apex Predator souls can only be obtained with strength if the player also has a stun item",
      "download_url": "https://github.com/Automagic00/R.E.P.O.-Archipelago-Client-Mod/releases/download/0.4.0/repo.apworld",
      "has_manifest": true,
      "hash_sha256": "34dec2fd298982fdae45c9a2f482e98c1ca4529c9b138658060287098c94fc41",
      "html_url": "https://github.com/Automagic00/R.E.P.O.-Archipelago-Client-Mod/releases/tag/0.4.0",
      "size": 18790,
      "source_url": "https://api.github.com/repos/Automagic00/R.E.P.O.-Archipelago-Client-Mod",
      "tag": "0.4.0",
      "title": "REPO Update 0.4.0",
      "version_simple": "0.4.0",
      "world_version": "0.4.0"
    }
  }
}
